mathscapes/__about__.py
mathscapes/__init__.py
mathscapes-0.0.1.dist-info/METADATA
mathscapes-0.0.1.dist-info/WHEEL
mathscapes-0.0.1.dist-info/licenses/LICENSE.txt
mathscapes-0.0.1.dist-info/RECORD
